{
  "en": [
    "invincible position"
  ], 
  "zh": "不败之地", 
  "en_related": [
    [
      "invincible position", 
      [
        "不败之地"
      ]
    ]
  ], 
  "ja_related": [
    [
      "不败之地", 
      [
        "無敵の", 
        "無敵", 
        "インヴィンシブル", 
        "インビンシブル"
      ]
    ], 
    [
      "不败之地", 
      [
        "位置", 
        "の位置", 
        "ポジション", 
        "た位置", 
        "位"
      ]
    ]
  ], 
  "zh_pronoun": "Bù bài zhī dì", 
  "ja": [
    "無敵の位置", 
    "Muteki no ichi"
  ]
}