{
  "en": [
    "serious"
  ], 
  "zh": "严重", 
  "en_related": [
    [
      "serious", 
      [
        "严重", 
        "认真", 
        "严肃", 
        "重", 
        "正经", 
        "沉重"
      ]
    ], 
    [
      "severe", 
      [
        "严重", 
        "严峻", 
        "严厉", 
        "剧烈", 
        "严格", 
        "严"
      ]
    ], 
    [
      "grave", 
      [
        "严重", 
        "严肃", 
        "庄重", 
        "严", 
        "忧", 
        "愔"
      ]
    ], 
    [
      "critical", 
      [
        "临界", 
        "严重", 
        "批评", 
        "危急", 
        "紧要", 
        "要紧"
      ]
    ]
  ], 
  "ja_related": [
    [
      "严重", 
      [
        "深刻", 
        "重大な", 
        "シリアス", 
        "真面目", 
        "に対する重篤な"
      ]
    ]
  ], 
  "zh_pronoun": "Yánzhòng", 
  "ja": [
    "深刻", 
    "Shinkoku"
  ]
}