{
  "en": [
    "personnel"
  ], 
  "zh": "人员", 
  "en_related": [
    [
      "personnel", 
      [
        "人员", 
        "人事", 
        "员工"
      ]
    ], 
    [
      "staff", 
      [
        "员工", 
        "人员", 
        "职工", 
        "标尺", 
        "杆", 
        "棍棒"
      ]
    ], 
    [
      "crew", 
      [
        "船员", 
        "人员", 
        "队", 
        "班组", 
        "全体人员"
      ]
    ]
  ], 
  "ja_related": [
    [
      "人员", 
      [
        "職員", 
        "人員", 
        "要員", 
        "の人員", 
        "人件"
      ]
    ]
  ], 
  "zh_pronoun": "Rényuán", 
  "ja": [
    "職員", 
    "Shokuin"
  ]
}