{
  "en": [
    "Make"
  ], 
  "zh": "做出", 
  "en_related": [
    [
      "issue", 
      [
        "发出", 
        "发布", 
        "颁发", 
        "发", 
        "发表", 
        "做出"
      ]
    ], 
    [
      "put out", 
      [
        "扑灭", 
        "灭", 
        "发行", 
        "做出", 
        "发放", 
        "发表"
      ]
    ]
  ], 
  "ja_related": [
    [
      "做出", 
      [
        "作ります", 
        "作る", 
        "メイク", 
        "する", 
        "ことを確認し"
      ]
    ]
  ], 
  "zh_pronoun": "Zuò chū", 
  "ja": [
    "作ります", 
    "Tsukurimasu"
  ]
}