{
  "en": [
    "cool"
  ], 
  "zh": "凉", 
  "en_related": [
    [
      "cool", 
      [
        "凉", 
        "凉爽", 
        "阴凉", 
        "冷静", 
        "沉着", 
        "风凉"
      ]
    ], 
    [
      "cold", 
      [
        "冷", 
        "寒", 
        "凉", 
        "冷淡", 
        "凛", 
        "凛凛"
      ]
    ], 
    [
      "disappointed", 
      [
        "败兴", 
        "恍", 
        "怃", 
        "惝", 
        "凉", 
        "壈"
      ]
    ], 
    [
      "discouraged", 
      [
        "灰心", 
        "泄气", 
        "气短", 
        "灰", 
        "凉", 
        "怆慌"
      ]
    ]
  ], 
  "ja_related": [
    [
      "凉", 
      [
        "クール", 
        "のクール", 
        "クール・", 
        "のクールな", 
        "クールな"
      ]
    ]
  ], 
  "zh_pronoun": "Liáng", 
  "ja": [
    "クール", 
    "Kūru"
  ]
}