{
  "en": [
    "practical"
  ], 
  "zh": "切实", 
  "en_related": [
    [
      "practical", 
      [
        "实用", 
        "实际", 
        "切实", 
        "落实"
      ]
    ], 
    [
      "realistic", 
      [
        "实际", 
        "切实"
      ]
    ], 
    [
      "feasible", 
      [
        "可行", 
        "切实", 
        "可能的"
      ]
    ]
  ], 
  "ja_related": [
    [
      "切实", 
      [
        "ひたすら", 
        "真剣に", 
        "熱心に", 
        "まじめに", 
        "くれぐれも"
      ]
    ]
  ], 
  "zh_pronoun": "Qièshí", 
  "ja": [
    "ひたすら", 
    "Hitasura"
  ]
}