{
  "en": [
    "pierce"
  ], 
  "zh": "刺穿", 
  "en_related": [
    [
      "pierce", 
      [
        "刺穿", 
        "穿", 
        "砭", 
        "戳", 
        "擘", 
        "插"
      ]
    ], 
    [
      "perforate", 
      [
        "穿孔", 
        "刺穿"
      ]
    ], 
    [
      "transfix", 
      [
        "刺穿"
      ]
    ], 
    [
      "spike", 
      [
        "抽穗", 
        "刺穿", 
        "扎透"
      ]
    ], 
    [
      "quill", 
      [
        "刺穿"
      ]
    ]
  ], 
  "ja_related": [
    [
      "刺穿", 
      [
        "ピアース", 
        "ピアス", 
        "刺す", 
        "穴を開ける", 
        "刺し通す"
      ]
    ]
  ], 
  "zh_pronoun": "Cì chuān", 
  "ja": [
    "ピアース", 
    "Piāsu"
  ]
}