{
  "en": [
    "inferiority"
  ], 
  "zh": "劣等", 
  "en_related": [
    [
      "inferiority", 
      [
        "劣等", 
        "不良", 
        "遜色", 
        "劣悪", 
        "低劣", 
        "劣弱"
      ]
    ], 
    [
      "low grade", 
      [
        "低級", 
        "低度", 
        "低劣", 
        "劣等", 
        "下等"
      ]
    ]
  ], 
  "ja_related": [], 
  "zh_pronoun": "Rettō", 
  "ja": [
    "Synonyms", 
    "    noun", 
    "        - 遜色, 拙悪, 不良, 悪質, 三流, 低級, 低劣, 下等", 
    "        - 遜色, 不良, 下級, 悪質, 三流, 低級, 低劣, 下位, 下等"
  ]
}