{
  "en": [
    "turmoil"
  ], 
  "zh": "动乱", 
  "en_related": [
    [
      "turmoil", 
      [
        "动荡", 
        "动乱", 
        "变乱"
      ]
    ], 
    [
      "upheaval", 
      [
        "动荡", 
        "动乱", 
        "隆起", 
        "乱"
      ]
    ], 
    [
      "disturbance", 
      [
        "风波", 
        "骚乱", 
        "动乱", 
        "骚动", 
        "事端", 
        "噪"
      ]
    ], 
    [
      "turbulence", 
      [
        "动乱", 
        "不稳定气流"
      ]
    ]
  ], 
  "ja_related": [
    [
      "动乱", 
      [
        "混乱", 
        "不安", 
        "市場の混乱", 
        "の混乱", 
        "動揺"
      ]
    ]
  ], 
  "zh_pronoun": "Dòngluàn", 
  "ja": [
    "混乱", 
    "Konran"
  ]
}