{
  "en": [
    "original"
  ], 
  "zh": "原始", 
  "en_related": [
    [
      "original", 
      [
        "原始", 
        "原", 
        "原来", 
        "原有", 
        "原先", 
        "新颖"
      ]
    ], 
    [
      "primitive", 
      [
        "原始", 
        "图元", 
        "原语"
      ]
    ], 
    [
      "primeval", 
      [
        "原始", 
        "初期的"
      ]
    ], 
    [
      "aboriginal", 
      [
        "土著", 
        "原始"
      ]
    ], 
    [
      "primaeval", 
      [
        "原始", 
        "初期的"
      ]
    ], 
    [
      "first", 
      [
        "第一", 
        "首先", 
        "初", 
        "首", 
        "头", 
        "原始"
      ]
    ], 
    [
      "first-hand", 
      [
        "第一手", 
        "原始", 
        "直接"
      ]
    ]
  ], 
  "ja_related": [
    [
      "原始", 
      [
        "オリジナル", 
        "元の", 
        "オリジナルの"
      ]
    ]
  ], 
  "zh_pronoun": "Yuánshǐ", 
  "ja": [
    "オリジナル", 
    "Orijinaru"
  ]
}