{
  "en": [
    "release"
  ], 
  "zh": "发布", 
  "en_related": [
    [
      "release", 
      [
        "推出", 
        "释放", 
        "发布", 
        "松开", 
        "发行", 
        "放出"
      ]
    ], 
    [
      "publish", 
      [
        "发布", 
        "发表", 
        "公布", 
        "出版", 
        "发行", 
        "布"
      ]
    ], 
    [
      "issue", 
      [
        "发出", 
        "发布", 
        "颁发", 
        "发", 
        "发表", 
        "颁布"
      ]
    ], 
    [
      "distribute", 
      [
        "分发", 
        "分配", 
        "发布", 
        "散发", 
        "发行", 
        "散布"
      ]
    ], 
    [
      "promulgate", 
      [
        "颁布", 
        "公布", 
        "发布", 
        "颁发", 
        "发表", 
        "颁"
      ]
    ], 
    [
      "print", 
      [
        "打印", 
        "印刷", 
        "印", 
        "刊", 
        "发布"
      ]
    ], 
    [
      "put out", 
      [
        "扑灭", 
        "灭", 
        "发行", 
        "做出", 
        "发放", 
        "发布"
      ]
    ]
  ], 
  "ja_related": [
    [
      "发布", 
      [
        "リリース", 
        "のリリース", 
        "リリースの", 
        "ます発売", 
        "公開"
      ]
    ]
  ], 
  "zh_pronoun": "Fābù", 
  "ja": [
    "リリース", 
    "Rirīsu"
  ]
}