{
  "en": [
    "shameful"
  ], 
  "zh": "可耻", 
  "en_related": [
    [
      "shameful", 
      [
        "可耻", 
        "不体面", 
        "丑", 
        "德行"
      ]
    ], 
    [
      "disgraceful", 
      [
        "可耻", 
        "不名誉", 
        "丑"
      ]
    ], 
    [
      "ignominious", 
      [
        "可耻"
      ]
    ], 
    [
      "opprobrious", 
      [
        "可耻", 
        "坏心肠的", 
        "凌辱的", 
        "无耻的", 
        "侮辱的"
      ]
    ]
  ], 
  "ja_related": [
    [
      "可耻", 
      [
        "恥ずべき", 
        "の恥ずかしい", 
        "恥ずべき", 
        "恥ずべきこと"
      ]
    ]
  ], 
  "zh_pronoun": "Kěchǐ", 
  "ja": [
    "恥ずべき", 
    "Hazubeki"
  ]
}