{
  "en": [
    "rationality"
  ], 
  "zh": "合理性", 
  "en_related": [
    [
      "consistency", 
      [
        "一致性", 
        "一致", 
        "浓度", 
        "论理", 
        "合理性", 
        "一贯性"
      ]
    ], 
    [
      "expedience", 
      [
        "便利", 
        "权", 
        "合理性"
      ]
    ], 
    [
      "expediency", 
      [
        "便利", 
        "权", 
        "合理性"
      ]
    ], 
    [
      "justifiability", 
      [
        "合理", 
        "合法性", 
        "合法", 
        "合理性"
      ]
    ], 
    [
      "rationality", 
      [
        "理性", 
        "合理性"
      ]
    ]
  ], 
  "ja_related": [
    [
      "合理", 
      [
        "合理性", 
        "合理性の", 
        "の合理性", 
        "の合理", 
        "合理"
      ]
    ]
  ], 
  "zh_pronoun": "Hélǐ xìng", 
  "ja": [
    "合理性", 
    "Gōri-sei"
  ]
}