{
  "en": [
    "companion"
  ], 
  "zh": "同伴", 
  "en_related": [
    [
      "companion", 
      [
        "伴侣", 
        "同伴", 
        "伙伴", 
        "伴", 
        "侣", 
        "伴星"
      ]
    ], 
    [
      "fellow", 
      [
        "家伙", 
        "同伴", 
        "朋友", 
        "佬", 
        "徒", 
        "汉"
      ]
    ], 
    [
      "partner", 
      [
        "伙伴", 
        "搭档", 
        "同伴", 
        "伴", 
        "股东", 
        "朋友"
      ]
    ], 
    [
      "comrade", 
      [
        "同志", 
        "同伴", 
        "朋友", 
        "合伙人", 
        "合夥人"
      ]
    ]
  ], 
  "ja_related": [
    [
      "同伴", 
      [
        "コンパニオン", 
        "仲間", 
        "コンパニオンの", 
        "のコンパニオン"
      ]
    ]
  ], 
  "zh_pronoun": "Tóngbàn", 
  "ja": [
    "コンパニオン", 
    "Konpanion"
  ]
}