{
  "en": [
    "pest"
  ], 
  "zh": "害虫", 
  "en_related": [
    [
      "pest", 
      [
        "害虫", 
        "疫病神", 
        "蟻巻", 
        "鼠疫", 
        "ペースト", 
        "やっかいもの"
      ]
    ], 
    [
      "vermin", 
      [
        "害虫", 
        "害鳥", 
        "蛔虫", 
        "蟻巻"
      ]
    ], 
    [
      "insect pest", 
      [
        "害虫", 
        "蛔虫"
      ]
    ], 
    [
      "harmful insect", 
      [
        "害虫", 
        "蛔虫"
      ]
    ]
  ], 
  "ja_related": [], 
  "zh_pronoun": "Gaichū", 
  "ja": [
    "See also", 
    "    虫, 害"
  ]
}