{
  "en": [
    "helper"
  ], 
  "zh": "帮手", 
  "en_related": [
    [
      "helper", 
      [
        "帮手", 
        "助手", 
        "帮工", 
        "义务", 
        "合作者"
      ]
    ], 
    [
      "assistant", 
      [
        "助理", 
        "助手", 
        "副", 
        "帮手", 
        "副手", 
        "辅导员"
      ]
    ], 
    [
      "helpmate", 
      [
        "帮手", 
        "合作者"
      ]
    ], 
    [
      "coadjutor", 
      [
        "帮手"
      ]
    ], 
    [
      "adjuvant", 
      [
        "帮手"
      ]
    ], 
    [
      "helpmeet", 
      [
        "帮手", 
        "合作者"
      ]
    ], 
    [
      "aider", 
      [
        "辅助", 
        "帮手"
      ]
    ]
  ], 
  "ja_related": [
    [
      "帮手", 
      [
        "ヘルパー", 
        "するヘルパー", 
        "ヘルパ", 
        "のヘルパー"
      ]
    ]
  ], 
  "zh_pronoun": "Bāngshǒu", 
  "ja": [
    "ヘルパー", 
    "Herupā"
  ]
}