{
  "en": [
    "solemn"
  ], 
  "zh": "庄严", 
  "en_related": [
    [
      "solemn", 
      [
        "庄严", 
        "庄重", 
        "严肃", 
        "隆重", 
        "俨然", 
        "严"
      ]
    ], 
    [
      "stately", 
      [
        "庄严", 
        "堂皇", 
        "威严", 
        "魁伟的"
      ]
    ], 
    [
      "dignified", 
      [
        "凝重", 
        "堂堂", 
        "端庄", 
        "威严", 
        "庄严", 
        "轩昂"
      ]
    ]
  ], 
  "ja_related": [
    [
      "庄严", 
      [
        "風格のあります", 
        "風格のある", 
        "堂々とした", 
        "厳か"
      ]
    ]
  ], 
  "zh_pronoun": "Zhuāngyán", 
  "ja": [
    "風格のあります", 
    "Fūkaku no arimasu"
  ]
}