{
  "en": [
    "wore"
  ], 
  "zh": "戴", 
  "en_related": [
    [
      "wear", 
      [
        "穿", 
        "戴", 
        "佩带", 
        "磨", 
        "佩", 
        "带"
      ]
    ], 
    [
      "put on", 
      [
        "穿", 
        "戴", 
        "披", 
        "抹", 
        "登", 
        "赢得"
      ]
    ], 
    [
      "bear", 
      [
        "承担", 
        "承受", 
        "忍受", 
        "负", 
        "结", 
        "戴"
      ]
    ], 
    [
      "honor", 
      [
        "兑现", 
        "褒", 
        "崇", 
        "戴", 
        "竦"
      ]
    ], 
    [
      "support", 
      [
        "支持", 
        "支撑", 
        "支援", 
        "支", 
        "帮助", 
        "戴"
      ]
    ], 
    [
      "honour", 
      [
        "兑现", 
        "褒", 
        "崇", 
        "戴", 
        "竦"
      ]
    ]
  ], 
  "ja_related": [
    [
      "戴", 
      [
        "着用", 
        "着る", 
        "摩耗", 
        "ウエア", 
        "損耗"
      ]
    ]
  ], 
  "zh_pronoun": "Dài", 
  "ja": [
    "着用", 
    "Chakuyō"
  ]
}