{
  "en": [
    "Opened"
  ], 
  "zh": "拉开", 
  "en_related": [
    [
      "undraw", 
      [
        "拉开"
      ]
    ], 
    [
      "unhinge", 
      [
        "拉开"
      ]
    ], 
    [
      "zip", 
      [
        "拉开"
      ]
    ], 
    [
      "rip", 
      [
        "刳", 
        "剖", 
        "歼", 
        "拉开", 
        "划开"
      ]
    ]
  ], 
  "ja_related": [
    [
      "拉开", 
      [
        "開設", 
        "開かれた", 
        "開いた", 
        "開か", 
        "開かれ"
      ]
    ]
  ], 
  "zh_pronoun": "Lā kāi", 
  "ja": [
    "開設", 
    "Kaisetsu"
  ]
}