{
  "en": [
    "Push"
  ], 
  "zh": "推", 
  "en_related": [
    [
      "push", 
      [
        "推", 
        "按", 
        "压", 
        "促进", 
        "促使", 
        "挤"
      ]
    ], 
    [
      "promote", 
      [
        "促进", 
        "推动", 
        "提升", 
        "促", 
        "提倡", 
        "推"
      ]
    ], 
    [
      "shove", 
      [
        "推", 
        "挤", 
        "猛推", 
        "放置", 
        "撞"
      ]
    ], 
    [
      "advance", 
      [
        "提前", 
        "推进", 
        "前进", 
        "促进", 
        "发展", 
        "推"
      ]
    ], 
    [
      "deduce", 
      [
        "推断", 
        "推", 
        "减掉", 
        "论断", 
        "意", 
        "臆测"
      ]
    ], 
    [
      "infer", 
      [
        "推断", 
        "比量", 
        "推", 
        "测", 
        "测度", 
        "论断"
      ]
    ], 
    [
      "postpone", 
      [
        "推迟", 
        "延迟", 
        "延期", 
        "顺延", 
        "延", 
        "推"
      ]
    ], 
    [
      "shift", 
      [
        "转移", 
        "移", 
        "移动", 
        "轮班", 
        "变", 
        "推"
      ]
    ], 
    [
      "shirk", 
      [
        "推脱", 
        "推卸", 
        "逃避", 
        "诿", 
        "推", 
        "辞"
      ]
    ], 
    [
      "pare", 
      [
        "削减", 
        "削", 
        "推", 
        "削皮"
      ]
    ], 
    [
      "refuse", 
      [
        "拒绝", 
        "拒", 
        "谢绝", 
        "推却", 
        "却", 
        "推"
      ]
    ], 
    [
      "choose", 
      [
        "选择", 
        "选", 
        "挑选", 
        "择", 
        "选购", 
        "推"
      ]
    ]
  ], 
  "ja_related": [
    [
      "推", 
      [
        "プッシュ", 
        "たプッシュ", 
        "の押し", 
        "を押し"
      ]
    ]
  ], 
  "zh_pronoun": "Tuī", 
  "ja": [
    "プッシュ", 
    "Pusshu"
  ]
}