{
  "en": [
    "Quantity"
  ], 
  "zh": "数量", 
  "en_related": [
    [
      "quantity", 
      [
        "数量", 
        "量", 
        "份量", 
        "额"
      ]
    ], 
    [
      "amount", 
      [
        "量", 
        "额", 
        "数量", 
        "多少", 
        "数目", 
        "数字"
      ]
    ]
  ], 
  "ja_related": [
    [
      "数量", 
      [
        "数量", 
        "量", 
        "分量", 
        "の数量", 
        "多量"
      ]
    ]
  ], 
  "zh_pronoun": "Shùliàng", 
  "ja": [
    "数量", 
    "Sūryō"
  ]
}