{
  "en": [
    "Day by day"
  ], 
  "zh": "日渐", 
  "en_related": [
    [
      "day by day", 
      [
        "日益", 
        "天天", 
        "日趋", 
        "逐日", 
        "日渐"
      ]
    ], 
    [
      "with each passing day", 
      [
        "日趋", 
        "日渐"
      ]
    ]
  ], 
  "ja_related": [
    [
      "日渐", 
      [
        "一日一日", 
        "一日一日と", 
        "日ごと", 
        "日ごとに", 
        "一日増しに"
      ]
    ]
  ], 
  "zh_pronoun": "Rìjiàn", 
  "ja": [
    "一日一日", 
    "Ichinichiichinichi"
  ]
}