{
  "en": [
    "impressive"
  ], 
  "zh": "有声有色", 
  "en_related": [
    [
      "impressive", 
      [
        "有声有色", 
        "优秀", 
        "威风", 
        "堂堂", 
        "荧", 
        "感人的"
      ]
    ], 
    [
      "vivid", 
      [
        "生动", 
        "传神", 
        "活灵活现", 
        "活泼", 
        "活", 
        "有声有色"
      ]
    ], 
    [
      "dramatic", 
      [
        "戏剧性", 
        "有声有色"
      ]
    ]
  ], 
  "ja_related": [
    [
      "有声有色", 
      [
        "印象的", 
        "印象的な", 
        "が印象的な", 
        "の印象的な"
      ]
    ]
  ], 
  "zh_pronoun": "Yǒushēngyǒusè", 
  "ja": [
    "印象的", 
    "Inshō-teki"
  ]
}