{
  "en": [
    "mode"
  ], 
  "zh": "模式", 
  "en_related": [
    [
      "mode", 
      [
        "模式", 
        "方式", 
        "状态", 
        "办法"
      ]
    ], 
    [
      "pattern", 
      [
        "模式", 
        "图案", 
        "格局", 
        "方式", 
        "型", 
        "样式"
      ]
    ], 
    [
      "method", 
      [
        "方法", 
        "办法", 
        "模式", 
        "术", 
        "作法", 
        "条理"
      ]
    ]
  ], 
  "ja_related": [
    [
      "模式", 
      [
        "モード", 
        "・モード", 
        "モードで", 
        "のモード", 
        "モードに"
      ]
    ]
  ], 
  "zh_pronoun": "Móshì", 
  "ja": [
    "モード", 
    "Mōdo"
  ]
}