{
  "en": [
    "water"
  ], 
  "zh": "水", 
  "en_related": [
    [
      "water", 
      [
        "水", 
        "雨水", 
        "泽", 
        "注入水"
      ]
    ], 
    [
      "liquid", 
      [
        "液体", 
        "液", 
        "水", 
        "液态水"
      ]
    ], 
    [
      "river", 
      [
        "河", 
        "河流", 
        "江", 
        "川", 
        "水"
      ]
    ]
  ], 
  "ja_related": [
    [
      "水", 
      [
        "水", 
        "た水", 
        "の水", 
        "ウォーター"
      ]
    ]
  ], 
  "zh_pronoun": "Shuǐ", 
  "ja": [
    "水", 
    "Mizu"
  ]
}