{
  "en": [
    "however"
  ], 
  "zh": "然而", 
  "en_related": [
    [
      "however", 
      [
        "然而", 
        "但是", 
        "但", 
        "不过", 
        "可是", 
        "却"
      ]
    ], 
    [
      "but", 
      [
        "但", 
        "但是", 
        "不过", 
        "而", 
        "可是", 
        "然而"
      ]
    ], 
    [
      "yet", 
      [
        "然而", 
        "但是", 
        "但", 
        "而", 
        "却", 
        "可"
      ]
    ]
  ], 
  "ja_related": [
    [
      "然而", 
      [
        "しかしながら", 
        "但し", 
        "ところが", 
        "しかし"
      ]
    ]
  ], 
  "zh_pronoun": "Rán'ér", 
  "ja": [
    "しかしながら", 
    "Shikashinagara"
  ]
}