{
  "en": [
    "Tow"
  ], 
  "zh": "牵引", 
  "en_related": [
    [
      "draw", 
      [
        "绘制", 
        "绘图", 
        "画", 
        "吸引", 
        "牵引", 
        "吸取"
      ]
    ], 
    [
      "drag", 
      [
        "拖动", 
        "拖", 
        "拖累", 
        "拖拉", 
        "曳", 
        "牵引"
      ]
    ], 
    [
      "tow", 
      [
        "拖", 
        "牵引", 
        "曳"
      ]
    ]
  ], 
  "ja_related": [
    [
      "牵引", 
      [
        "トウ", 
        "けん引", 
        "曳航", 
        "牽引", 
        "Towの"
      ]
    ]
  ], 
  "zh_pronoun": "Qiānyǐn", 
  "ja": [
    "トウ", 
    "Tō"
  ]
}