{
  "en": [
    "phenomenon"
  ], 
  "zh": "现象", 
  "en_related": [
    [
      "phenomenon", 
      [
        "现象", 
        "特殊的事物"
      ]
    ], 
    [
      "appearance", 
      [
        "出现", 
        "外形", 
        "外貌", 
        "样子", 
        "模样", 
        "现象"
      ]
    ]
  ], 
  "ja_related": [
    [
      "现象", 
      [
        "現象", 
        "という現象", 
        "の現象", 
        "フェノメナ", 
        "する現象"
      ]
    ]
  ], 
  "zh_pronoun": "Xiànxiàng", 
  "ja": [
    "現象", 
    "Genshō"
  ]
}