{
  "en": [
    "by"
  ], 
  "zh": "由", 
  "en_related": [
    [
      "by", 
      [
        "通过", 
        "由", 
        "以", 
        "将", 
        "靠", 
        "截至"
      ]
    ], 
    [
      "from", 
      [
        "从", 
        "由", 
        "自", 
        "离", 
        "从中", 
        "阻止"
      ]
    ], 
    [
      "due to", 
      [
        "由于", 
        "由", 
        "基于", 
        "承", 
        "定于"
      ]
    ], 
    [
      "because of", 
      [
        "由于", 
        "基于", 
        "由", 
        "冲"
      ]
    ], 
    [
      "to", 
      [
        "于", 
        "至", 
        "对", 
        "向", 
        "给", 
        "由"
      ]
    ], 
    [
      "per", 
      [
        "每", 
        "由"
      ]
    ]
  ], 
  "ja_related": [
    [
      "由", 
      [
        "によって", 
        "ことで", 
        "ことにより", 
        "から"
      ]
    ]
  ], 
  "zh_pronoun": "Yóu", 
  "ja": [
    "によって", 
    "Ni yotte"
  ]
}