{
  "en": [
    "meet"
  ], 
  "zh": "碰见", 
  "en_related": [
    [
      "meet", 
      [
        "满足", 
        "见", 
        "会面", 
        "见面", 
        "迎接", 
        "碰见"
      ]
    ], 
    [
      "run in", 
      [
        "拘留", 
        "碰", 
        "碰见", 
        "碰撞", 
        "撞"
      ]
    ]
  ], 
  "ja_related": [
    [
      "碰见", 
      [
        "大会", 
        "ミート", 
        "会う", 
        "と出会う", 
        "に会う"
      ]
    ]
  ], 
  "zh_pronoun": "Pèngjiàn", 
  "ja": [
    "大会", 
    "Taikai"
  ]
}