{
  "en": [
    "just"
  ], 
  "zh": "祇是", 
  "en_related": [
    [
      "just", 
      [
        "祇是", 
        "剛剛", 
        "祇", 
        "剛", 
        "剛好", 
        "才"
      ]
    ], 
    [
      "simply", 
      [
        "祇是", 
        "根本", 
        "簡直", 
        "乾脆", 
        "死活", 
        "順手"
      ]
    ]
  ], 
  "ja_related": [
    [
      "只是", 
      [
        "ただ", 
        "ちょうど", 
        "単に", 
        "ばかり", 
        "だけ"
      ]
    ]
  ], 
  "zh_pronoun": "Qíshì", 
  "ja": [
    "ただ", 
    "Tada"
  ]
}