{
  "en": [
    "Academy of sciences"
  ], 
  "zh": "科学院", 
  "en_related": [
    [
      "academy of sciences", 
      [
        "科学院"
      ]
    ]
  ], 
  "ja_related": [
    [
      "科学院", 
      [
        "科学", 
        "の科学", 
        "サイエンス分野", 
        "学", 
        "・サイエンス"
      ]
    ], 
    [
      "科学院", 
      [
        "アカデミー", 
        "・アカデミー", 
        "アカデミー・オブ", 
        "はアカデミーオブ", 
        "アカデミー・オブ・"
      ]
    ]
  ], 
  "zh_pronoun": "Kēxuéyuàn", 
  "ja": [
    "科学アカデミー", 
    "Kagaku akademī"
  ]
}