{
  "en": [
    "space"
  ], 
  "zh": "空间", 
  "en_related": [
    [
      "space", 
      [
        "空间", 
        "间隙", 
        "场地", 
        "间距", 
        "篇幅", 
        "空地"
      ]
    ], 
    [
      "room", 
      [
        "房间", 
        "间", 
        "房", 
        "室", 
        "空间", 
        "余地"
      ]
    ], 
    [
      "void", 
      [
        "空间", 
        "空虚", 
        "虚"
      ]
    ], 
    [
      "airspace", 
      [
        "空域", 
        "空间", 
        "广播时间"
      ]
    ], 
    [
      "interspace", 
      [
        "空隙", 
        "空间"
      ]
    ], 
    [
      "vacuum", 
      [
        "真空", 
        "空间"
      ]
    ], 
    [
      "roomage", 
      [
        "空间"
      ]
    ], 
    [
      "expanse", 
      [
        "广阔", 
        "宽阔", 
        "辽阔", 
        "空间"
      ]
    ]
  ], 
  "ja_related": [
    [
      "空间", 
      [
        "スペース", 
        "空間", 
        "宇宙", 
        "スペース・", 
        "・スペース"
      ]
    ]
  ], 
  "zh_pronoun": "Kōngjiān", 
  "ja": [
    "スペース", 
    "Supēsu"
  ]
}