{
  "en": [
    "sports"
  ], 
  "zh": "竞技", 
  "en_related": [
    [
      "sports", 
      [
        "体育", 
        "运动", 
        "竞技"
      ]
    ], 
    [
      "athletics", 
      [
        "竞技", 
        "运动", 
        "田径运动"
      ]
    ], 
    [
      "tournament", 
      [
        "比赛", 
        "竞技", 
        "竞争"
      ]
    ]
  ], 
  "ja_related": [
    [
      "竞技", 
      [
        "スポーツの", 
        "・スポーツ", 
        "のスポーツ施設", 
        "スポツ"
      ]
    ]
  ], 
  "zh_pronoun": "Jìngjì", 
  "ja": [
    "スポーツの", 
    "Supōtsu no"
  ]
}