{
  "en": [
    "clever"
  ], 
  "zh": "聪明", 
  "en_related": [
    [
      "clever", 
      [
        "聪明", 
        "巧妙", 
        "高明", 
        "机灵", 
        "乖巧", 
        "灵"
      ]
    ], 
    [
      "intelligent", 
      [
        "智能", 
        "聪明", 
        "聪慧", 
        "聪颖", 
        "慧", 
        "心灵"
      ]
    ], 
    [
      "bright", 
      [
        "光亮", 
        "光明", 
        "辉", 
        "明", 
        "晖", 
        "聪明"
      ]
    ]
  ], 
  "ja_related": [
    [
      "聪明", 
      [
        "賢いです", 
        "賢い", 
        "巧妙な", 
        "クレバー", 
        "に巧妙な"
      ]
    ]
  ], 
  "zh_pronoun": "Cōngmíng", 
  "ja": [
    "賢いです", 
    "Kashikoidesu"
  ]
}