{
  "en": [
    "Model"
  ], 
  "zh": "范", 
  "en_related": [
    [
      "model", 
      [
        "模型", 
        "型号", 
        "型", 
        "机型", 
        "模", 
        "范"
      ]
    ], 
    [
      "limits", 
      [
        "范围", 
        "范"
      ]
    ], 
    [
      "pattern", 
      [
        "模式", 
        "图案", 
        "格局", 
        "方式", 
        "型", 
        "范"
      ]
    ], 
    [
      "example", 
      [
        "例", 
        "例子", 
        "范例", 
        "榜样", 
        "典范", 
        "范"
      ]
    ]
  ], 
  "ja_related": [
    [
      "范", 
      [
        "モデル", 
        "・モデル", 
        "のモデル", 
        "たモデル"
      ]
    ]
  ], 
  "zh_pronoun": "Fàn", 
  "ja": [
    "モデル", 
    "Moderu"
  ]
}