{
  "en": [
    "candle"
  ], 
  "zh": "蜡烛", 
  "en_related": [
    [
      "candle", 
      [
        "蜡烛", 
        "烛", 
        "蜡"
      ]
    ], 
    [
      "wax candle", 
      [
        "蜡烛"
      ]
    ], 
    [
      "bougie", 
      [
        "蜡烛"
      ]
    ]
  ], 
  "ja_related": [
    [
      "蜡烛", 
      [
        "キャンドル", 
        "ろうそく", 
        "ロウソク", 
        "のろうそく", 
        "ろうそくの"
      ]
    ]
  ], 
  "zh_pronoun": "Làzhú", 
  "ja": [
    "キャンドル", 
    "Kyandoru"
  ]
}