{
  "en": [
    "Zhan Hua Xun"
  ], 
  "zh": "詹勳华", 
  "en_related": [], 
  "ja_related": [
    [
      "詹", 
      [
        "Zhanの", 
        "占", 
        "ZHAN"
      ]
    ], 
    [
      "华", 
      [
        "華", 
        "ホア", 
        "ホワ", 
        "フア", 
        "ホアヒン"
      ]
    ], 
    [
      "勋", 
      [
        "魯迅", 
        "ジョウシュン", 
        "迅", 
        "シュン", 
        "勳"
      ]
    ]
  ], 
  "zh_pronoun": "Zhānxūnhuá", 
  "ja": [
    "Zhanの華魯迅", 
    "Zhan no Hana Rojin"
  ]
}