{
  "en": [
    "evidence"
  ], 
  "zh": "证据", 
  "en_related": [
    [
      "evidence", 
      [
        "证据", 
        "表明", 
        "明显", 
        "佐证", 
        "凭证", 
        "据"
      ]
    ], 
    [
      "proof", 
      [
        "证明", 
        "证据", 
        "证", 
        "论证", 
        "凭证", 
        "凭据"
      ]
    ], 
    [
      "testimony", 
      [
        "见证", 
        "证词", 
        "证明", 
        "证据"
      ]
    ]
  ], 
  "ja_related": [
    [
      "证据", 
      [
        "証拠", 
        "の証拠", 
        "兆候", 
        "形跡", 
        "な証拠"
      ]
    ]
  ], 
  "zh_pronoun": "Zhèngjù", 
  "ja": [
    "証拠", 
    "Shōko"
  ]
}