{
  "en": [
    "complain"
  ], 
  "zh": "诉苦", 
  "en_related": [
    [
      "complain", 
      [
        "抱怨", 
        "怨", 
        "发牢骚", 
        "诉苦", 
        "控告", 
        "诼"
      ]
    ], 
    [
      "whine", 
      [
        "发牢骚", 
        "诉苦", 
        "酸", 
        "议论"
      ]
    ], 
    [
      "lament", 
      [
        "哀叹", 
        "悲叹", 
        "哀", 
        "诉苦", 
        "悼", 
        "轸"
      ]
    ], 
    [
      "grumble", 
      [
        "叽", 
        "抱怨", 
        "发牢骚", 
        "噜", 
        "怨言", 
        "诉苦"
      ]
    ], 
    [
      "lodge a complaint", 
      [
        "诉", 
        "诉苦"
      ]
    ], 
    [
      "make a complaint", 
      [
        "诉", 
        "诉苦"
      ]
    ], 
    [
      "murmur", 
      [
        "私语", 
        "潺潺", 
        "咕哝", 
        "讟", 
        "耳语", 
        "诉苦"
      ]
    ], 
    [
      "bemoan one's fate", 
      [
        "诉苦"
      ]
    ], 
    [
      "cry on shoulder", 
      [
        "诉苦"
      ]
    ]
  ], 
  "ja_related": [
    [
      "诉苦", 
      [
        "文句を言います", 
        "文句を言う", 
        "不平を言う", 
        "訴える", 
        "不満を言う"
      ]
    ]
  ], 
  "zh_pronoun": "Sùkǔ", 
  "ja": [
    "文句を言います", 
    "Monku o iimasu"
  ]
}