{
  "en": [
    "read"
  ], 
  "zh": "读", 
  "en_related": [
    [
      "read", 
      [
        "读", 
        "阅读", 
        "读书", 
        "看", 
        "阅", 
        "阅览"
      ]
    ], 
    [
      "study", 
      [
        "研究", 
        "学习", 
        "学", 
        "考察", 
        "研", 
        "读"
      ]
    ], 
    [
      "learn", 
      [
        "学习", 
        "学", 
        "学会", 
        "得知", 
        "记住", 
        "读"
      ]
    ], 
    [
      "attend school", 
      [
        "上学", 
        "求学", 
        "读书", 
        "读"
      ]
    ]
  ], 
  "ja_related": [
    [
      "读", 
      [
        "読みます", 
        "読む", 
        "リード", 
        "読み込み", 
        "記事を読む"
      ]
    ]
  ], 
  "zh_pronoun": "Dú", 
  "ja": [
    "読みます", 
    "Yomimasu"
  ]
}