{
  "en": [
    "Chao Jung-tai"
  ], 
  "zh": "赵荣台", 
  "en_related": null, 
  "ja_related": [
    [
      "赵荣", 
      [
        "チャオ", 
        "・チャオ", 
        "チャオ・", 
        "のチャオ", 
        "チャオの"
      ]
    ], 
    [
      "赵荣", 
      [
        "チョン", 
        "ユング", 
        "ジョン", 
        "ジュン", 
        "チョン・"
      ]
    ], 
    [
      "赵荣 台", 
      [
        "隊", 
        "太極拳"
      ]
    ]
  ], 
  "zh_pronoun": "Zhàoróngtái", 
  "ja": [
    "チャオチョン隊", 
    "Chaochon-tai"
  ]
}