{
  "en": [
    "enough"
  ], 
  "zh": "足够", 
  "en_related": [
    [
      "enough", 
      [
        "足够", 
        "足以", 
        "足", 
        "够数"
      ]
    ], 
    [
      "sufficient", 
      [
        "足够", 
        "充", 
        "足以", 
        "充足", 
        "足", 
        "够"
      ]
    ], 
    [
      "adequate", 
      [
        "充足", 
        "足够", 
        "适当", 
        "够"
      ]
    ], 
    [
      "ample", 
      [
        "充足", 
        "充分", 
        "丰满", 
        "足够", 
        "丰富", 
        "足"
      ]
    ]
  ], 
  "ja_related": [
    [
      "足够", 
      [
        "十分な", 
        "十分に", 
        "の十分な", 
        "に十分", 
        "イナフ"
      ]
    ]
  ], 
  "zh_pronoun": "Zúgòu", 
  "ja": [
    "十分な", 
    "Jūbun'na"
  ]
}