{
  "en": [
    "delivery"
  ], 
  "zh": "输送", 
  "en_related": [
    [
      "delivery", 
      [
        "交货", 
        "输送", 
        "输", 
        "娩", 
        "发出", 
        "发行"
      ]
    ], 
    [
      "transport", 
      [
        "运输", 
        "输送", 
        "运", 
        "转运", 
        "输", 
        "航运"
      ]
    ], 
    [
      "transportation", 
      [
        "运输", 
        "输送", 
        "运", 
        "输", 
        "转运"
      ]
    ], 
    [
      "conveyance", 
      [
        "输送", 
        "运送", 
        "运输", 
        "运输工具", 
        "运", 
        "输"
      ]
    ], 
    [
      "supply", 
      [
        "输送", 
        "输"
      ]
    ]
  ], 
  "ja_related": [
    [
      "输送", 
      [
        "配信", 
        "配達", 
        "配送", 
        "デリバリー", 
        "引き渡し"
      ]
    ]
  ], 
  "zh_pronoun": "Shūsòng", 
  "ja": [
    "配信", 
    "Haishin"
  ]
}