{
  "en": [
    "Again"
  ], 
  "zh": "重新", 
  "en_related": [
    [
      "again", 
      [
        "再次", 
        "再", 
        "重新", 
        "又", 
        "重", 
        "复"
      ]
    ], 
    [
      "anew", 
      [
        "重新", 
        "再", 
        "新近"
      ]
    ], 
    [
      "afresh", 
      [
        "重新"
      ]
    ]
  ], 
  "ja_related": [
    [
      "重新", 
      [
        "再び", 
        "再度", 
        "もやはり", 
        "ここでもまた", 
        "もう"
      ]
    ]
  ], 
  "zh_pronoun": "Chóngxīn", 
  "ja": [
    "再び", 
    "Futatabi"
  ]
}