{
  "en": [
    "Forte"
  ], 
  "zh": "长处", 
  "en_related": [
    [
      "merit", 
      [
        "优点", 
        "功", 
        "长处", 
        "绩", 
        "勋", 
        "体面"
      ]
    ], 
    [
      "forte", 
      [
        "长处"
      ]
    ], 
    [
      "strong point", 
      [
        "优点", 
        "长处", 
        "特长", 
        "据点"
      ]
    ]
  ], 
  "ja_related": [
    [
      "长处", 
      [
        "フォルテ", 
        "得意", 
        "フォルテ・", 
        "お手の物", 
        "の得意"
      ]
    ]
  ], 
  "zh_pronoun": "Chángchu", 
  "ja": [
    "フォルテ", 
    "Forute"
  ]
}