{
  "en": [
    "Precipitous"
  ], 
  "zh": "陡峭", 
  "en_related": [
    [
      "precipitous", 
      [
        "陡峭", 
        "陡", 
        "峭", 
        "嶒", 
        "崔", 
        "嶡"
      ]
    ], 
    [
      "cliffy", 
      [
        "陡峭", 
        "笔峭"
      ]
    ]
  ], 
  "ja_related": [
    [
      "陡峭", 
      [
        "険しいです", 
        "険しい", 
        "急峻な", 
        "切り立った", 
        "急激"
      ]
    ]
  ], 
  "zh_pronoun": "Dǒuqiào", 
  "ja": [
    "険しいです", 
    "Kewashīdesu"
  ]
}