{
  "en": [
    "food"
  ], 
  "zh": "食品", 
  "en_related": [
    [
      "food", 
      [
        "食品", 
        "食物", 
        "粮食", 
        "食", 
        "粮", 
        "餐"
      ]
    ], 
    [
      "foodstuff", 
      [
        "食品", 
        "粮食"
      ]
    ], 
    [
      "grocery", 
      [
        "食品", 
        "副食商店"
      ]
    ], 
    [
      "provisions", 
      [
        "食品", 
        "粮"
      ]
    ]
  ], 
  "ja_related": [
    [
      "食品", 
      [
        "食品", 
        "食べ物", 
        "フード", 
        "食物", 
        "食料"
      ]
    ]
  ], 
  "zh_pronoun": "Shípǐn", 
  "ja": [
    "食品", 
    "Shokuhin"
  ]
}