{
  "en": [
    "spirits"
  ], 
  "zh": "鬼神", 
  "en_related": [
    [
      "spirits", 
      [
        "鬼神", 
        "酒"
      ]
    ], 
    [
      "ghosts and gods", 
      [
        "鬼神"
      ]
    ], 
    [
      "supernatural being", 
      [
        "神仙", 
        "鬼神"
      ]
    ]
  ], 
  "ja_related": [
    [
      "鬼神", 
      [
        "スピリッツ", 
        "のスピリッツ", 
        "スピリット", 
        "の霊", 
        "精霊"
      ]
    ]
  ], 
  "zh_pronoun": "Guǐshén", 
  "ja": [
    "スピリッツ", 
    "Supirittsu"
  ]
}